fvhd/__init__.py
fvhd/config.py
fvhd/fvhd.py
knn/__init__.py
knn/base.py
knn/generator.py
knn/graph.py
fvhd-0.2.0.dist-info/METADATA
fvhd-0.2.0.dist-info/WHEEL
fvhd-0.2.0.dist-info/licenses/LICENSE.md
fvhd-0.2.0.dist-info/RECORD
