Metadata-Version: 2.4
Name: fvhd
Version: 0.2.0
Summary: Fast visualization of high-dimensional data
Author-email: Bartosz Minch <minch@agh.edu.pl>, Filip Ręka <filipreka@agh.edu.pl>
License: MIT
License-File: LICENSE.md
Requires-Python: <3.15,>=3.14.0
Requires-Dist: numpy>=2.2.2
Requires-Dist: pandas>=2.2.3
Requires-Dist: pydantic>=2.0.0
Requires-Dist: scikit-learn>=1.6.1
Requires-Dist: torch>=2.5.1
Requires-Dist: ty>=0.0.14
